<title>Release Notes</title>
<productname>Red Hat Virtualization</productname>
<productnumber>{vernum_rhv}</productnumber>
<subtitle>Release notes for Red Hat Virtualization {vernum_rhv}</subtitle>
<abstract><para>The Release Notes provide high-level coverage of the improvements and additions that have been implemented in Red Hat Virtualization {vernum_rhv}.</para>
<!--<para>{beta-disclaimer}</para>--></abstract>
<authorgroup id="Author_Group">
	<author>
		<firstname>Red Hat Virtualization</firstname><surname>Documentation Team</surname>
		<affiliation>
			<orgname>
				Red Hat
			</orgname>
			<orgdiv>
				Customer Content Services
			</orgdiv>
		</affiliation><email>rhev-docs@redhat.com</email>
	</author>
</authorgroup>
